landfire/__init__.py
landfire/geospatial.py
landfire/product/enums.py
landfire/product/models.py
landfire/product/search.py
landfire/product/utils.py
landfire/py.typed
landfire-0.5.0.dist-info/LICENSE
landfire-0.5.0.dist-info/WHEEL
landfire-0.5.0.dist-info/METADATA
landfire-0.5.0.dist-info/RECORD
