Metadata-Version: 2.1
Name: landfire
Version: 0.5.0
Summary: Landfire
Home-page: https://github.com/FireSci/landfire-python
License: MIT
Author: FireSci
Author-email: support@firesci.io
Requires-Python: >=3.8,<3.12
Classifier: Development Status :: 4 - Beta
Classifier: Intended Audience :: Developers
Classifier: License :: OSI Approved :: MIT License
Classifier: Programming Language :: Python
Classifier: Programming Language :: Python :: 3
Classifier: Programming Language :: Python :: 3.8
Classifier: Programming Language :: Python :: 3.9
Classifier: Programming Language :: Python :: 3.10
Classifier: Programming Language :: Python :: 3.11
Classifier: Typing :: Typed
Provides-Extra: geospatial
Requires-Dist: attrs (>=22.2.0)
Requires-Dist: fiona (>=1.9.0) ; extra == "geospatial"
Requires-Dist: geojson (>=3.0.0) ; extra == "geospatial"
Requires-Dist: geopandas (>=0.12.0) ; extra == "geospatial"
Requires-Dist: pydantic (>=1.10)
Requires-Dist: requests (>=2.28.0)
Requires-Dist: tqdm (>=4.65.0,<5.0.0)
Project-URL: Changelog, https://github.com/FireSci/landfire-python/releases
Project-URL: Documentation, https://landfire-python.firesci.io
Project-URL: Repository, https://github.com/FireSci/landfire-python
